mkdocs_drawio/__init__.py
mkdocs_drawio/css/drawio-darkmode.css
mkdocs_drawio/plugin.py
mkdocs_drawio-1.13.0.dist-info/METADATA
mkdocs_drawio-1.13.0.dist-info/WHEEL
mkdocs_drawio-1.13.0.dist-info/entry_points.txt
mkdocs_drawio-1.13.0.dist-info/licenses/LICENSE
mkdocs_drawio-1.13.0.dist-info/RECORD
