Metadata-Version: 2.4
Name: mkdocs-drawio
Version: 1.13.0
Summary: MkDocs plugin for embedding Drawio files
License: MIT
License-File: LICENSE
Keywords: mkdocs,plugin,markdown,drawio
Author: Jan Larwig
Author-email: jan@larwig.com
Requires-Python: >=3.8.0,<4.0
Classifier: License :: OSI Approved :: MIT License
Classifier: Programming Language :: Python :: 3
Classifier: Programming Language :: Python :: 3.8
Classifier: Programming Language :: Python :: 3.9
Classifier: Programming Language :: Python :: 3.10
Classifier: Programming Language :: Python :: 3.11
Classifier: Programming Language :: Python :: 3.12
Classifier: Programming Language :: Python :: 3.13
Classifier: Programming Language :: Python :: 3.14
Requires-Dist: Jinja2 (>=3.0)
Requires-Dist: beautifulsoup4 (>=4.0)
Requires-Dist: lxml (>=4.8)
Requires-Dist: mkdocs (>=1.4)
Requires-Dist: requests (>=2.0)
Project-URL: Homepage, https://github.com/tuunit/mkdocs-drawio/
Project-URL: Repository, https://github.com/tuunit/mkdocs-drawio/
